<Interaction Type="FAQ" ContentFolder="proj_content" Title="Definition: An Adult at Risk" Numbering="0" animation="fade" contentfont="Articulate" jpegquality="80" autoplay="false" autoplayduration="5" headingfont="Articulate" navfont="Articulate" soundeffects="true" volumebutton="true" audioquality="low" audiocustombitrate="br112Kbps" audiocustomfrequency="fq12KHz" audiocustomchannel="ccMono" navbuttons="false" forceorder="false" detectflashver="true" version="2.3.1009.1313" borderstyle="round_inset">
  <Search enabled="false" searchtext="Search" resulttext="found for" />
  <steps>
    <Step id="a2cf97c0-3cd5-46c4-bf03-9f2e9784793c" name="An Adult at Risk is defined as:-" title="" number="" html="&lt;p align='left'&gt;&lt;font face='Articulate' size='13' color=''&gt;A person aged 18 years or over:-&lt;br&gt;&lt;/br&gt;&lt;/font&gt;&lt;/p&gt;&lt;p align='left'&gt;&lt;font face='Articulate' size='13' color=''&gt;&lt;b&gt;'who is or may be in need of community care services by reason of mental or other disability, age or illness; and who is or may be unable to take care of him or herself or unable to protect him or herself against significant harm or exploitation’&lt;/b&gt;&lt;/font&gt;&lt;/p&gt;&lt;p align='left'&gt;&lt;font face='Articulate' size='13' color=''&gt;&lt;i&gt;(Department of Health, 2000)&lt;br&gt;&lt;/br&gt;&lt;/i&gt;&lt;/font&gt;&lt;/p&gt;&lt;p align='left'&gt;&lt;font face='Articulate' size='13' color=''&gt;Community care services include all care services provided in any setting e.g. hospitals, residential homes, nursing homes, day services, domiciliary care, respite and voluntary services. These services may be for adults with a physical, learning or mental disability.&lt;br&gt;&lt;/br&gt;&lt;/font&gt;&lt;/p&gt;&lt;p align='left'&gt;&lt;font face='Articulate' size='13' color=''&gt;The term 'adult at risk' has been used to replace 'vulnerable adult'.&lt;/font&gt;&lt;/p&gt;" intro="true">
      <image width="150" height="203" zoomheight="520" playbar="false" autoplay="false" zoomwidth="382" zoommode="Embedded" allowzoom="false" align="topright" duration="0" framerate="30" name="image0.jpg" zoomimage="" />
    </Step>
    <Step id="bd277f39-06ba-46b7-9b6c-bb360230cf4f" name="An Adult at Risk may therefore be a person who:-" title="" number="" html="&lt;p align='left'&gt;&lt;textformat tabstops='[0]' indent='-20' leftmargin='40'&gt;&lt;font face='Articulate' size='13' color=''&gt;•&lt;TAB&gt;&lt;/TAB&gt;is elderly and frail due to ill health, physical disability or cognitive impairment&lt;br&gt;&lt;/br&gt;&lt;/font&gt;&lt;/textformat&gt;&lt;/p&gt;&lt;p align='left'&gt;&lt;textformat tabstops='[0]' indent='-20' leftmargin='40'&gt;&lt;font face='Articulate' size='13' color=''&gt;•&lt;TAB&gt;&lt;/TAB&gt;has a learning disability&lt;br&gt;&lt;/br&gt;&lt;/font&gt;&lt;/textformat&gt;&lt;/p&gt;&lt;p align='left'&gt;&lt;textformat tabstops='[0]' indent='-20' leftmargin='40'&gt;&lt;font face='Articulate' size='13' color=''&gt;•&lt;TAB&gt;&lt;/TAB&gt;has a physical disability and/or a sensory impairment&lt;br&gt;&lt;/br&gt;&lt;/font&gt;&lt;/textformat&gt;&lt;/p&gt;&lt;p align='left'&gt;&lt;textformat tabstops='[0]' indent='-20' leftmargin='40'&gt;&lt;font face='Articulate' size='13' color=''&gt;•&lt;TAB&gt;&lt;/TAB&gt;has mental health needs including dementia or a personality disorder&lt;br&gt;&lt;/br&gt;&lt;/font&gt;&lt;/textformat&gt;&lt;/p&gt;&lt;p align='left'&gt;&lt;textformat tabstops='[0]' indent='-20' leftmargin='40'&gt;&lt;font face='Articulate' size='13' color=''&gt;•&lt;TAB&gt;&lt;/TAB&gt;has a long term illness/condition&lt;br&gt;&lt;/br&gt;&lt;/font&gt;&lt;/textformat&gt;&lt;/p&gt;&lt;p align='left'&gt;&lt;textformat tabstops='[0]' indent='-20' leftmargin='40'&gt;&lt;font face='Articulate' size='13' color=''&gt;•&lt;TAB&gt;&lt;/TAB&gt;misuses substances or alcohol&lt;br&gt;&lt;/br&gt;&lt;/font&gt;&lt;/textformat&gt;&lt;/p&gt;&lt;p align='left'&gt;&lt;textformat tabstops='[0]' indent='-20' leftmargin='40'&gt;&lt;font face='Articulate' size='13' color=''&gt;•&lt;TAB&gt;&lt;/TAB&gt;is unable to demonstrate the capacity to make a decision and is in need of care and support.&lt;/font&gt;&lt;/textformat&gt;&lt;/p&gt;">
      <image width="150" height="198" zoomheight="520" playbar="false" autoplay="false" zoomwidth="393" zoommode="Embedded" allowzoom="false" align="topright" duration="0" framerate="30" name="image1.jpg" zoomimage="" />
    </Step>
  </steps>
  <starttip show="false" text="Click next to continue" />
  <resume id="a8f990af-6393-4830-8adc-216388d8302e" enabled="false" />
</Interaction>